binsync/__init__.py
binsync/__main__.py
binsync/binsync_plugin.py
binsync/configuration.py
binsync/controller.py
binsync/installer.py
binsync/loggercfg.py
binsync/core/__init__.py
binsync/core/cache.py
binsync/core/client.py
binsync/core/errors.py
binsync/core/scheduler.py
binsync/core/state.py
binsync/core/user.py
binsync/extras/__init__.py
binsync/extras/aux_server/__init__.py
binsync/extras/aux_server/aux_client.py
binsync/extras/aux_server/aux_server.py
binsync/extras/aux_server/store.py
binsync/interface_overrides/__init__.py
binsync/interface_overrides/angr.py
binsync/interface_overrides/binja.py
binsync/interface_overrides/ghidra.py
binsync/interface_overrides/ida.py
binsync/stub_files/README.md
binsync/stub_files/__init__.py
binsync/stub_files/binsync_binja_logo.png
binsync/stub_files/ida-plugin.json
binsync/stub_files/plugin.json
binsync/stub_files/requirements.txt
binsync/stub_files/angr_files/__init__.py
binsync/stub_files/angr_files/plugin.toml
binsync/ui/__init__.py
binsync/ui/config_dialog.py
binsync/ui/control_panel.py
binsync/ui/function_merge_dialog.py
binsync/ui/magic_sync_dialog.py
binsync/ui/pull_segments_dialog.py
binsync/ui/utils.py
binsync/ui/force_push/__init__.py
binsync/ui/force_push/force_push.py
binsync/ui/force_push/panels/__init__.py
binsync/ui/force_push/panels/functions_table.py
binsync/ui/force_push/panels/globals_table.py
binsync/ui/force_push/panels/segments_table.py
binsync/ui/force_push/panels/table_model.py
binsync/ui/panel_tabs/__init__.py
binsync/ui/panel_tabs/activity_table.py
binsync/ui/panel_tabs/ctx_table.py
binsync/ui/panel_tabs/functions_table.py
binsync/ui/panel_tabs/globals_table.py
binsync/ui/panel_tabs/table_model.py
binsync/ui/panel_tabs/util_panel.py
binsync/ui/progress_graph/__init__.py
binsync/ui/progress_graph/progress_window.py
binsync/ui/progress_graph/summarize.py
binsync-5.11.2.dist-info/licenses/LICENSE
binsync-5.11.2.dist-info/METADATA
binsync-5.11.2.dist-info/WHEEL
binsync-5.11.2.dist-info/entry_points.txt
binsync-5.11.2.dist-info/top_level.txt
binsync-5.11.2.dist-info/RECORD
