Metadata-Version: 2.4
Name: binsync
Version: 5.11.2
Summary: A Collaboration framework for binary analysis tasks.
License: BSD 2 Clause
Project-URL: Homepage, https://github.com/binsync/binsync
Classifier: License :: OSI Approved :: BSD License
Classifier: Programming Language :: Python :: 3
Classifier: Programming Language :: Python :: 3.10
Classifier: Programming Language :: Python :: 3.12
Requires-Python: >=3.10
License-File: LICENSE
Requires-Dist: libbs[ghidra]>=3.3.3
Requires-Dist: sortedcontainers
Requires-Dist: toml
Requires-Dist: GitPython
Requires-Dist: filelock
Requires-Dist: pycparser
Requires-Dist: ply
Requires-Dist: prompt_toolkit
Requires-Dist: tqdm
Requires-Dist: wordfreq
Provides-Extra: test
Requires-Dist: pytest-qt; extra == "test"
Requires-Dist: flake8; extra == "test"
Requires-Dist: pytest; extra == "test"
Provides-Extra: extras
Requires-Dist: dailalib; extra == "extras"
Requires-Dist: flask; extra == "extras"
Requires-Dist: requests; extra == "extras"
Dynamic: license-file
